iterativeWGCNA/__init__.py
iterativeWGCNA/__main__.py
iterativeWGCNA/analysis.py
iterativeWGCNA/cmlargs.py
iterativeWGCNA/colors.py
iterativeWGCNA/eigengenes.py
iterativeWGCNA/expression.py
iterativeWGCNA/genes.py
iterativeWGCNA/iterativeWGCNA.py
iterativeWGCNA/network.py
iterativeWGCNA/wgcna.py
iterativeWGCNA/io/__init__.py
iterativeWGCNA/io/utils.py
iterativeWGCNA/r/__init__.py
iterativeWGCNA/r/imports.py
iterativeWGCNA/r/manager.py
iterativeWGCNA/r/snippets.py
iterativeWGCNA-1.1.6.data/scripts/iterativeWGCNA
iterativeWGCNA-1.1.6.data/scripts/iterativeWGCNA_merge
iterativeWGCNA-1.1.6.dist-info/DESCRIPTION.rst
iterativeWGCNA-1.1.6.dist-info/METADATA
iterativeWGCNA-1.1.6.dist-info/RECORD
iterativeWGCNA-1.1.6.dist-info/WHEEL
iterativeWGCNA-1.1.6.dist-info/metadata.json
iterativeWGCNA-1.1.6.dist-info/top_level.txt
