Metadata-Version: 2.0
Name: iterativeWGCNA
Version: 1.1.6
Summary: Iterative application of WGCNA
Home-page: http://github.com/cstoeckert/iterativeWGCNA
Author: Emily Greenfest-Allen
Author-email: allenem@pennmedicine.upenn.edu
License: GNU
Download-URL: https://github.com/cstoeckert/iterativeWGCNA/archive/v1.1.6.tar.gz
Keywords: network,WGCNA,gene expression,bioinformatics
Platform: UNKNOWN
Requires-Dist: rpy2
Requires-Dist: matplotlib
